svg_flatten_wasi/__init__.py
svg_flatten_wasi/svg-flatten.wasm
svg_flatten_wasi-3.1.9.dist-info/METADATA
svg_flatten_wasi-3.1.9.dist-info/WHEEL
svg_flatten_wasi-3.1.9.dist-info/entry_points.txt
svg_flatten_wasi-3.1.9.dist-info/top_level.txt
svg_flatten_wasi-3.1.9.dist-info/RECORD
